[
  {
    "index": 0,
    "key": "EVENT__BAR__BAR_18_0000",
    "original": "ん？　海底神殿の骨董品の話？\nあぁ、あの壺のこと？\nアレは高値で売れたねー。\\r\n地下１４階の[COLOR 0005]北西の通路[COLOR 0000]にある\nガラクタの山から見つけたんだよ。\\r\n…あれ？　もしかして僕があっさり\n教えちゃったからビックリしてる？\\r\n宝物がまだ残ってるんだったら\n普通は教えないよねー。\\r\nうん。つまり、そういうこと。\\r\nあぁ、それでも行くんだ？\nアンタたち変わってんのな。\nまぁ、好きにしなよ。",
    "translation": "ん？　海底神殿の骨董品の話？\nあぁ、あの壺のこと？\nアレは高値で売れたねー。\\r\n地下１４階の[COLOR 0005]北西の通路[COLOR 0000]にある\nガラクタの山から見つけたんだよ。\\r\n…あれ？　もしかして僕があっさり\n教えちゃったからビックリしてる？\\r\n宝物がまだ残ってるんだったら\n普通は教えないよねー。\\r\nうん。つまり、そういうこと。\\r\nあぁ、それでも行くんだ？\nアンタたち変わってんのな。\nまぁ、好きにしなよ。",
    "suffix": "\n[END]"
  }
]