[
  {
    "index": 0,
    "key": "EVENT__BAR__BAR_10_0000",
    "original": "…これか？　これはお化けドリアンの\n刺身じゃよ。この店の名物料理じゃ。\\r\nこんなに美味い[COLOR 0005]お化けドリアン[COLOR 0000]じゃが\n[COLOR 0005]タイタンアルム[COLOR 0000]とセットで現れた\nときは注意が必要じゃな。\\r\nタイタンアルムは一見鮮やかな\n花じゃが、綺麗な花には棘…\nではないが臭いが凄まじいのじゃ。\\r\n想像を絶する悪臭が\nお互いに作用し合ってひどい目に\n合うこと請け合いじゃ。\\r\n…おーい、ねーちゃん！\nタイタンアルムの漬物はまだかのー？",
    "translation": "…これか？　これはお化けドリアンの\n刺身じゃよ。この店の名物料理じゃ。\\r\nこんなに美味い[COLOR 0005]お化けドリアン[COLOR 0000]じゃが\n[COLOR 0005]タイタンアルム[COLOR 0000]とセットで現れた\nときは注意が必要じゃな。\\r\nタイタンアルムは一見鮮やかな\n花じゃが、綺麗な花には棘…\nではないが臭いが凄まじいのじゃ。\\r\n想像を絶する悪臭が\nお互いに作用し合ってひどい目に\n合うこと請け合いじゃ。\\r\n…おーい、ねーちゃん！\nタイタンアルムの漬物はまだかのー？",
    "suffix": "\n[END]"
  }
]